LICENSE
io_orbit/__init__.py
io_orbit/__main__.py
io_orbit/cloud_configurations/__init__.py
io_orbit/cloud_configurations/firebase_client.py
io_orbit/cloud_configurations/google_client.py
io_orbit/events/__init__.py
io_orbit/events/event_producer.py
io_orbit/events/event_receiver.py
io_orbit/events/exchange_producer.py
io_orbit/events/exchange_receiver.py
io_orbit/logger/__init__.py
io_orbit/logger/laccuna_logging.py
io_orbit/logger/logger_helper.py
io_orbit/workflow/__init__.py
io_orbit/workflow/workflow_helper.py
io_orbit-0.0.8.dist-info/entry_points.txt
io_orbit-0.0.8.dist-info/LICENSE
io_orbit-0.0.8.dist-info/WHEEL
io_orbit-0.0.8.dist-info/METADATA
io_orbit-0.0.8.dist-info/RECORD
